<metadata xml:lang="en"><Esri><CreaDate>20111013</CreaDate><CreaTime>17021600</CreaTime><SyncOnce>FALSE</SyncOnce><SyncDate>20120416</SyncDate><SyncTime>14372900</SyncTime><ModDate>20120416</ModDate><ModTime>14372900</ModTime><DataProperties><lineage><Process ToolSource="C:\Program Files\ArcGIS\ArcToolbox\Toolboxes\Data Management Tools.tbx\CopyFeatures" Date="20100708" Time="112734">CopyFeatures u:\projects\special_purpose_projects\4m_territories\park\polygon U:\Projects\special_purpose_projects\4m_territories\territories4m.gdb\park_polygon # 0 0 0</Process><Process ToolSource="C:\Program Files\ArcGIS\ArcToolbox\Toolboxes\Data Management Tools.tbx\CopyFeatures" Date="20101201" Time="123035">CopyFeatures U:\Maps\ReferenceMaps\Territories4m\Year2010\territories4m.gdb\LCC\park_polygon U:\Maps\ReferenceMaps\Territories4m\Year2010\terr4M_old_layers.gdb\LCC\park_polygon # 0 0 0</Process><Process ToolSource="C:\Program Files\ArcGIS\Desktop10.0\ArcToolbox\Toolboxes\Data Management Tools.tbx\CopyFeatures" Date="20110428" Time="143612">CopyFeatures E:\Greenland\copyTerr4m\territories4m.gdb\LCC\park_polygon U:\Maps\ReferenceMaps\Territories4m\Year2010\Data_gdb_etc\compilation.gdb\LCC_NAD83\park_polygon # 0 0 0</Process><Process ToolSource="C:\Program Files\ArcGIS\Desktop10.0\ArcToolbox\Toolboxes\Conversion Tools.tbx\FeatureClassToFeatureClass" Date="20110510" Time="164833">FeatureClassToFeatureClass U:\Maps\ReferenceMaps\Territories4m\Year2010\Data_gdb_etc\compilation.gdb\LCC_NAD83\park_2000_p U:\Maps\ReferenceMaps\Territories4m\Year2010\Data_gdb_etc\compilation.gdb\LCC_NAD83 park_2011_p # "PARK_ID "PARK_ID" true true false 4 Long 0 0 ,First,#,U:\Maps\ReferenceMaps\Territories4m\Year2010\Data_gdb_etc\compilation.gdb\LCC_NAD83\park_2000_p,PARK_ID,-1,-1;Shape_Length "Shape_Length" false true true 8 Double 0 0 ,First,#,U:\Maps\ReferenceMaps\Territories4m\Year2010\Data_gdb_etc\compilation.gdb\LCC_NAD83\park_2000_p,Shape_Length,-1,-1;Shape_Area "Shape_Area" false true true 8 Double 0 0 ,First,#,U:\Maps\ReferenceMaps\Territories4m\Year2010\Data_gdb_etc\compilation.gdb\LCC_NAD83\park_2000_p,Shape_Area,-1,-1" #</Process><Process ToolSource="C:\Program Files\ArcGIS\Desktop10.0\ArcToolbox\Toolboxes\Data Management Tools.tbx\AddField" Date="20110605" Time="170711">AddField U:\Maps\ReferenceMaps\Territories4m\Year2010\Data_gdb_etc\compilation.gdb\LCC_NAD83\park_2011_p CARTO_UID LONG # # # # NULLABLE NON_REQUIRED #</Process><Process ToolSource="C:\Program Files\ArcGIS\Desktop10.0\ArcToolbox\Toolboxes\Data Management Tools.tbx\CalculateField" Date="20110605" Time="171313">CalculateField park_2011_p NOTE [Comment] VB #</Process><Process ToolSource="C:\Program Files\ArcGIS\Desktop10.0\ArcToolbox\Toolboxes\Data Management Tools.tbx\AddField" Date="20110605" Time="171452">AddField U:\Maps\ReferenceMaps\Territories4m\Year2010\Data_gdb_etc\compilation.gdb\LCC_NAD83\park_2011_p COMMENT TEXT # # 150 # NULLABLE NON_REQUIRED #</Process><Process ToolSource="C:\Program Files\ArcGIS\Desktop10.0\ArcToolbox\Toolboxes\Data Management Tools.tbx\CalculateField" Date="20110605" Time="182550">CalculateField park_2011_p CARTO_UID 0 VB #</Process><Process ToolSource="C:\Program Files\ArcGIS\Desktop10.0\ArcToolbox\Toolboxes\Data Management Tools.tbx\CalculateField" Date="20110605" Time="182602">CalculateField park_2011_p CARTO_UID 10 VB #</Process><Process ToolSource="C:\Program Files\ArcGIS\Desktop10.0\ArcToolbox\Toolboxes\Data Management Tools.tbx\CalculateField" Date="20110607" Time="091843">CalculateField park_2011_p CARTO_UID 0
 VB #</Process><Process ToolSource="C:\Program Files\ArcGIS\Desktop10.0\ArcToolbox\Toolboxes\Data Management Tools.tbx\CalculateField" Date="20110607" Time="093001">CalculateField park_2011_p CARTO_UID 0 VB #</Process><Process ToolSource="C:\Program Files\ArcGIS\Desktop10.0\ArcToolbox\Toolboxes\Data Management Tools.tbx\CalculateField" Date="20110607" Time="150411">CalculateField park_2011_p CLASS "National Park (terrestrial)" VB #</Process><Process ToolSource="C:\Program Files\ArcGIS\Desktop10.0\ArcToolbox\Toolboxes\Data Management Tools.tbx\CalculateField" Date="20110607" Time="150519">CalculateField park_2011_p CLASS "Marine Protected Area (federal)" VB #</Process><Process ToolSource="C:\Program Files\ArcGIS\Desktop10.0\ArcToolbox\Toolboxes\Data Management Tools.tbx\CalculateField" Date="20110607" Time="150604">CalculateField park_2011_p CLASS "Marine Protected Area (federal)" VB #</Process><Process ToolSource="C:\Program Files\ArcGIS\Desktop10.0\ArcToolbox\Toolboxes\Data Management Tools.tbx\CalculateField" Date="20110607" Time="150649">CalculateField park_2011_p CLASS "National Park"
 VB #</Process><Process ToolSource="C:\Program Files\ArcGIS\Desktop10.0\ArcToolbox\Toolboxes\Data Management Tools.tbx\CalculateField" Date="20110607" Time="150725">CalculateField park_2011_p CLASS "other parks"
 VB #</Process><Process ToolSource="C:\Program Files\ArcGIS\Desktop10.0\ArcToolbox\Toolboxes\Data Management Tools.tbx\CalculateField" Date="20110721" Time="100653">CalculateField park_2011_p NOTE_ "water portion from old protected areas" VB #</Process><Process ToolSource="C:\Program Files\ArcGIS\Desktop10.0\ArcToolbox\Toolboxes\Data Management Tools.tbx\CalculateField" Date="20110721" Time="100715">CalculateField park_2011_p COMMENT "water portion from old protected areas" VB #</Process><Process ToolSource="C:\Program Files\ArcGIS\Desktop10.0\ArcToolbox\Toolboxes\Data Management Tools.tbx\CalculateField" Date="20110721" Time="100741">CalculateField park_2011_p COMMENT "water portion from old protected areas" VB #</Process><Process ToolSource="C:\Program Files\ArcGIS\Desktop10.0\ArcToolbox\Toolboxes\Data Management Tools.tbx\CalculateField" Date="20110721" Time="101412">CalculateField park_2011_p COMMENT "Other Protecte Area" VB #</Process><Process ToolSource="C:\Program Files\ArcGIS\Desktop10.0\ArcToolbox\Toolboxes\Data Management Tools.tbx\CalculateField" Date="20110721" Time="101424">CalculateField park_2011_p COMMENT "Other Protected Area" VB #</Process><Process ToolSource="C:\Program Files\ArcGIS\Desktop10.0\ArcToolbox\Toolboxes\Data Management Tools.tbx\CalculateField" Date="20110721" Time="101436">CalculateField park_2011_p COMMENT "Other Protected Area" VB #</Process><Process ToolSource="C:\Program Files\ArcGIS\Desktop10.0\ArcToolbox\Toolboxes\Data Management Tools.tbx\CalculateField" Date="20110721" Time="101449">CalculateField park_2011_p COMMENT "Other Protected Area" VB #</Process><Process ToolSource="C:\Program Files\ArcGIS\Desktop10.0\ArcToolbox\Toolboxes\Data Management Tools.tbx\CalculateField" Date="20110721" Time="101915">CalculateField park_2011_p CLASS "Other Protected Area" VB #</Process><Process ToolSource="C:\Program Files\ArcGIS\Desktop10.0\ArcToolbox\Toolboxes\Data Management Tools.tbx\CalculateField" Date="20110817" Time="145041">CalculateField "park_2011_p [50%]" FR_SPEC "YES" VB #</Process><Process ToolSource="C:\Program Files\ArcGIS\Desktop10.0\ArcToolbox\Toolboxes\Conversion Tools.tbx\FeatureClassToFeatureClass" Date="20110818" Time="153131">FeatureClassToFeatureClass U:\Maps\ReferenceMaps\Territories4m\Year2010\Data_gdb_etc\nat_pk_+_100_ha.shp U:\Maps\ReferenceMaps\Territories4m\Year2010\Data_gdb_etc\compilation.gdb nat_pk_and_100_ha # "OBJECTID "OBJECTID" true true false 9 Long 0 9 ,First,#,U:\Maps\ReferenceMaps\Territories4m\Year2010\Data_gdb_etc\nat_pk_+_100_ha.shp,OBJECTID,-1,-1;PARK_ID "PARK_ID" true true false 9 Long 0 9 ,First,#,U:\Maps\ReferenceMaps\Territories4m\Year2010\Data_gdb_etc\nat_pk_+_100_ha.shp,PARK_ID,-1,-1;NAME "NAME" true true false 100 Text 0 0 ,First,#,U:\Maps\ReferenceMaps\Territories4m\Year2010\Data_gdb_etc\nat_pk_+_100_ha.shp,NAME,-1,-1;NOM "NOM" true true false 100 Text 0 0 ,First,#,U:\Maps\ReferenceMaps\Territories4m\Year2010\Data_gdb_etc\nat_pk_+_100_ha.shp,NOM,-1,-1;USER_NAME "USER_NAME" true true false 10 Text 0 0 ,First,#,U:\Maps\ReferenceMaps\Territories4m\Year2010\Data_gdb_etc\nat_pk_+_100_ha.shp,USER_NAME,-1,-1;EDIT_DATE "EDIT_DATE" true true false 8 Date 0 0 ,First,#,U:\Maps\ReferenceMaps\Territories4m\Year2010\Data_gdb_etc\nat_pk_+_100_ha.shp,EDIT_DATE,-1,-1;CARTO_UID "CARTO_UID" true true false 9 Long 0 9 ,First,#,U:\Maps\ReferenceMaps\Territories4m\Year2010\Data_gdb_etc\nat_pk_+_100_ha.shp,CARTO_UID,-1,-1;COMMENT "COMMENT" true true false 150 Text 0 0 ,First,#,U:\Maps\ReferenceMaps\Territories4m\Year2010\Data_gdb_etc\nat_pk_+_100_ha.shp,COMMENT,-1,-1;CLASS "CLASS" true true false 40 Text 0 0 ,First,#,U:\Maps\ReferenceMaps\Territories4m\Year2010\Data_gdb_etc\nat_pk_+_100_ha.shp,CLASS,-1,-1;FEAT_TYPE "FEAT_TYPE" true true false 50 Text 0 0 ,First,#,U:\Maps\ReferenceMaps\Territories4m\Year2010\Data_gdb_etc\nat_pk_+_100_ha.shp,FEAT_TYPE,-1,-1;Area "Area" true true false 19 Double 0 0 ,First,#,U:\Maps\ReferenceMaps\Territories4m\Year2010\Data_gdb_etc\nat_pk_+_100_ha.shp,Area,-1,-1;FR_SPEC "FR_SPEC" true true false 10 Text 0 0 ,First,#,U:\Maps\ReferenceMaps\Territories4m\Year2010\Data_gdb_etc\nat_pk_+_100_ha.shp,FR_SPEC,-1,-1" #</Process><Process ToolSource="C:\Program Files\ArcGIS\Desktop10.0\ArcToolbox\Toolboxes\Data Management Tools.tbx\CalculateField" Date="20111005" Time="122450">CalculateField nat_pk_and_100_ha follows "y"
 VB #</Process><Process ToolSource="C:\Program Files\ArcGIS\Desktop10.0\ArcToolbox\Toolboxes\Data Management Tools.tbx\CalculateField" Date="20111005" Time="141041">CalculateField nat_pk_and_100_ha Water 0
 VB #</Process><Process ToolSource="C:\Program Files\ArcGIS\Desktop10.0\ArcToolbox\Toolboxes\Data Management Tools.tbx\CalculateField" Date="20111005" Time="141105">CalculateField nat_pk_and_100_ha Water 1

 VB #</Process><Process ToolSource="C:\Program Files\ArcGIS\Desktop10.0\ArcToolbox\Toolboxes\Data Management Tools.tbx\CalculateField" Date="20111005" Time="141125">CalculateField nat_pk_and_100_ha Water 0

 VB #</Process><Process ToolSource="C:\Program Files\ArcGIS\Desktop10.0\ArcToolbox\Toolboxes\Data Management Tools.tbx\CalculateField" Date="20111005" Time="141145">CalculateField nat_pk_and_100_ha verif "y"
 VB #</Process><Process ToolSource="C:\Program Files\ArcGIS\Desktop10.0\ArcToolbox\Toolboxes\Data Management Tools.tbx\CalculateField" Date="20111005" Time="141152">CalculateField nat_pk_and_100_ha follows "y"
 VB #</Process><Process ToolSource="C:\Program Files\ArcGIS\Desktop10.0\ArcToolbox\Toolboxes\Data Management Tools.tbx\CalculateField" Date="20111005" Time="141432">CalculateField nat_pk_and_100_ha Water 0

 VB #</Process><Process ToolSource="C:\Program Files\ArcGIS\Desktop10.0\ArcToolbox\Toolboxes\Data Management Tools.tbx\CopyFeatures" Date="20111107" Time="113234">CopyFeatures "P:\North of 60\Compilation_November\compilation.gdb\LCC_NAD83\ProtAreas_2011_p" U:\Maps\ReferenceMaps\Territories4m\Year2010\Data_gdb_etc\compilation.gdb\LCC_NAD83\ProtAreas_2011_p # 0 0 0</Process><Process ToolSource="C:\Program Files\ArcGIS\Desktop10.0\ArcToolbox\Toolboxes\Data Management Tools.tbx\CalculateField" Date="20111108" Time="164623">CalculateField ProtAreas_2011_p VERIF_ANDY "" VB #</Process><Process ToolSource="C:\Program Files\ArcGIS\Desktop10.0\ArcToolbox\Toolboxes\Data Management Tools.tbx\CalculateField" Date="20111109" Time="095507">CalculateField "ProtAreas_2011_p  [DQ]" DISPLAY 1 VB #</Process><Process ToolSource="C:\Program Files\ArcGIS\Desktop10.0\ArcToolbox\Toolboxes\Data Management Tools.tbx\CalculateField" Date="20111109" Time="095600">CalculateField "ProtAreas_2011_p  [DQ]" DISPLAY 0
 VB #</Process><Process ToolSource="C:\Program Files\ArcGIS\Desktop10.0\ArcToolbox\Toolboxes\Data Management Tools.tbx\CalculateField" Date="20111109" Time="100710">CalculateField "ProtAreas_2011_p  [DQ]" DISPLAY 0

 VB #</Process><Process ToolSource="C:\Program Files\ArcGIS\Desktop10.0\ArcToolbox\Toolboxes\Data Management Tools.tbx\CalculateField" Date="20111109" Time="100722">CalculateField "ProtAreas_2011_p  [DQ]" Water 0

 VB #</Process><Process ToolSource="C:\Program Files\ArcGIS\Desktop10.0\ArcToolbox\Toolboxes\Data Management Tools.tbx\CalculateField" Date="20111110" Time="162502">CalculateField "ProtAreas_2011_p  [DQ]" PARK_ID 0
 VB #</Process><Process ToolSource="C:\Program Files\ArcGIS\Desktop10.0\ArcToolbox\Toolboxes\Data Management Tools.tbx\CalculateField" Date="20111110" Time="162606">CalculateField "ProtAreas_2011_p  [DQ]" FILL 0
 VB #</Process><Process ToolSource="C:\Program Files\ArcGIS\Desktop10.0\ArcToolbox\Toolboxes\Data Management Tools.tbx\CalculateField" Date="20111110" Time="162640">CalculateField "ProtAreas_2011_p  [DQ]" FILL [CLASS2] VB #</Process><Process ToolSource="C:\Program Files\ArcGIS\Desktop10.0\ArcToolbox\Toolboxes\Data Management Tools.tbx\CalculateField" Date="20111110" Time="162754">CalculateField "ProtAreas_2011_p  [DQ]" FILL "[CLASS2] +5
" VB #</Process><Process ToolSource="C:\Program Files\ArcGIS\Desktop10.0\ArcToolbox\Toolboxes\Data Management Tools.tbx\CalculateField" Date="20120201" Time="125727">CalculateField "XX ProtAreas_2011_p" CARTO_UID "[OBJECTID_1] * 1000 + 43" VB #</Process><Process ToolSource="C:\Program Files\ArcGIS\Desktop10.0\ArcToolbox\Toolboxes\Data Management Tools.tbx\CalculateField" Date="20120306" Time="090637">CalculateField ProtAreas_2011_p NOM_FR [NOM] VB #</Process><Process ToolSource="C:\Program Files\ArcGIS\Desktop10.0\ArcToolbox\Toolboxes\Data Management Tools.tbx\CalculateField" Date="20120306" Time="090700">CalculateField ProtAreas_2011_p NAME_EN [NAME] VB #</Process><Process ToolSource="C:\Program Files\ArcGIS\Desktop10.0\ArcToolbox\Toolboxes\Data Management Tools.tbx\CalculateField" Date="20120306" Time="091040">CalculateField ProtAreas_2011_p TYPE MPA VB #</Process><Process ToolSource="C:\Program Files\ArcGIS\Desktop10.0\ArcToolbox\Toolboxes\Data Management Tools.tbx\CalculateField" Date="20120306" Time="091055">CalculateField ProtAreas_2011_p TYPE "MPA" VB #</Process><Process ToolSource="C:\Program Files\ArcGIS\Desktop10.0\ArcToolbox\Toolboxes\Data Management Tools.tbx\CalculateField" Date="20120306" Time="091138">CalculateField ProtAreas_2011_p TYPE "MBS" VB #</Process><Process ToolSource="C:\Program Files\ArcGIS\Desktop10.0\ArcToolbox\Toolboxes\Data Management Tools.tbx\CalculateField" Date="20120306" Time="091309">CalculateField ProtAreas_2011_p TYPE "NP" VB #</Process><Process ToolSource="C:\Program Files\ArcGIS\Desktop10.0\ArcToolbox\Toolboxes\Data Management Tools.tbx\CalculateField" Date="20120306" Time="091356">CalculateField ProtAreas_2011_p TYPE "NWA" VB #</Process><Process ToolSource="C:\Program Files\ArcGIS\Desktop10.0\ArcToolbox\Toolboxes\Data Management Tools.tbx\CalculateField" Date="20120306" Time="092424">CalculateField ProtAreas_2011_p FEATURE_E [FEAT_TYPE] VB #</Process><Process ToolSource="C:\Program Files\ArcGIS\Desktop10.0\ArcToolbox\Toolboxes\Data Management Tools.tbx\CalculateField" Date="20120306" Time="092503">CalculateField ProtAreas_2011_p FEATURE_F [FEATURE_E] VB #</Process><Process ToolSource="C:\Program Files\ArcGIS\Desktop10.0\ArcToolbox\Toolboxes\Data Management Tools.tbx\CalculateField" Date="20120306" Time="092644">CalculateField ProtAreas_2011_p CLASS [CLASS2] VB #</Process><Process ToolSource="C:\Program Files\ArcGIS\Desktop10.0\ArcToolbox\Toolboxes\Data Management Tools.tbx\CalculateField" Date="20120306" Time="110204">CalculateField ProtAreas_2011_p WATER_COMP [Water] VB #</Process><Process ToolSource="C:\Program Files\ArcGIS\Desktop10.0\ArcToolbox\Toolboxes\Data Management Tools.tbx\CopyFeatures" Date="20120416" Time="143729">CopyFeatures U:\Maps\ReferenceMaps\Territories4m\Year2010\COPYV1RELEASE\compilation_20120216.gdb\LCC_NAD83\prot_areas_p U:\Maps\ReferenceMaps\Territories4m\Year2010\COPYV1RELEASE\shapefiles\prot_areas_p.shp # 0 0 0</Process></lineage><itemProps><itemName Sync="TRUE">prot_areas_p</itemName><imsContentType Sync="TRUE">002</imsContentType><itemLocation><linkage Sync="TRUE">file://\\s0-bsc-fs02\Atlas\Maps\ReferenceMaps\Territories4m\Year2010\COPYV1RELEASE\shapefiles\LCC_NAD83\prot_areas_p</linkage><protocol Sync="TRUE">Local Area Network</protocol></itemLocation><itemSize Sync="TRUE">0.000</itemSize></itemProps><coordRef><type Sync="TRUE">Projected</type><geogcsn Sync="TRUE">GCS_North_American_1983</geogcsn><projcsn Sync="TRUE">NAD_1983_Terr4M</projcsn><peXml Sync="TRUE">&lt;ProjectedCoordinateSystem xsi:type='typens:ProjectedCoordinateSystem' xmlns:xsi='http://www.w3.org/2001/XMLSchema-instance' xmlns:xs='http://www.w3.org/2001/XMLSchema' xmlns:typens='http://www.esri.com/schemas/ArcGIS/10.0'&gt;&lt;WKT&gt;PROJCS[&amp;quot;NAD_1983_Terr4M&amp;quot;,GEOGCS[&amp;quot;GCS_North_American_1983&amp;quot;,DATUM[&amp;quot;D_North_American_1983&amp;quot;,SPHEROID[&amp;quot;GRS_1980&amp;quot;,6378137.0,298.257222101]],PRIMEM[&amp;quot;Greenwich&amp;quot;,0.0],UNIT[&amp;quot;Degree&amp;quot;,0.0174532925199433]],PROJECTION[&amp;quot;Lambert_Conformal_Conic&amp;quot;],PARAMETER[&amp;quot;False_Easting&amp;quot;,0.0],PARAMETER[&amp;quot;False_Northing&amp;quot;,0.0],PARAMETER[&amp;quot;Central_Meridian&amp;quot;,-105.0],PARAMETER[&amp;quot;Standard_Parallel_1&amp;quot;,60.0],PARAMETER[&amp;quot;Standard_Parallel_2&amp;quot;,75.0],PARAMETER[&amp;quot;Latitude_Of_Origin&amp;quot;,60.0],UNIT[&amp;quot;Meter&amp;quot;,1.0]]&lt;/WKT&gt;&lt;XOrigin&gt;-34686200&lt;/XOrigin&gt;&lt;YOrigin&gt;-31235900&lt;/YOrigin&gt;&lt;XYScale&gt;129838368.78558317&lt;/XYScale&gt;&lt;ZOrigin&gt;-100000&lt;/ZOrigin&gt;&lt;ZScale&gt;10000&lt;/ZScale&gt;&lt;MOrigin&gt;-100000&lt;/MOrigin&gt;&lt;MScale&gt;10000&lt;/MScale&gt;&lt;XYTolerance&gt;0.001&lt;/XYTolerance&gt;&lt;ZTolerance&gt;0.001&lt;/ZTolerance&gt;&lt;MTolerance&gt;0.001&lt;/MTolerance&gt;&lt;HighPrecision&gt;true&lt;/HighPrecision&gt;&lt;/ProjectedCoordinateSystem&gt;</peXml></coordRef><copyHistory><copy source="U:\Maps\ReferenceMaps\Territories4m\Year2010\COPYV1RELEASE\shapefiles\prot_areas_p" dest="\\s0-bsc-fs02\Atlas\Maps\ReferenceMaps\Territories4m\Year2010\COPYV1RELEASE\shapefiles\LCC_NAD83\prot_areas_p" date="20120424" time="08590100"></copy></copyHistory></DataProperties><ArcGISFormat>1.0</ArcGISFormat><ArcGISstyle>North American Profile of ISO19115 2003</ArcGISstyle></Esri><idinfo><native Sync="TRUE">Microsoft Windows XP Version 5.1 (Build 2600) Service Pack 3; ESRI ArcCatalog 9.3.1.4000</native><descript><langdata Sync="TRUE">en</langdata><abstract>REQUIRED: A brief narrative summary of the data set.</abstract><purpose>REQUIRED: A summary of the intentions with which the data set was developed.</purpose></descript><citation><citeinfo><origin>REQUIRED: The name of an organization or individual that developed the data set.</origin><pubdate>REQUIRED: The date when the data set is published or otherwise made available for release.</pubdate><title Sync="TRUE">park_polygon</title><ftname Sync="TRUE">park_polygon</ftname><geoform Sync="TRUE">vector digital data</geoform><onlink Sync="TRUE">\\s0-bsc-fs02\Atlas\Maps\ReferenceMaps\Territories4m\Year2010\terr4M_old_layers.gdb</onlink></citeinfo></citation><timeperd><current>REQUIRED: The basis on which the time period of content information is determined.</current><timeinfo><sngdate><caldate>REQUIRED: The year (and optionally month, or month and day) for which the data set corresponds to the ground.</caldate></sngdate></timeinfo></timeperd><status><progress>REQUIRED: The state of the data set.</progress><update>REQUIRED: The frequency with which changes and additions are made to the data set after the initial data set is completed.</update></status><spdom><bounding><westbc Sync="TRUE">REQUIRED: Western-most coordinate of the limit of coverage expressed in longitude.</westbc><eastbc Sync="TRUE">REQUIRED: Eastern-most coordinate of the limit of coverage expressed in longitude.</eastbc><northbc Sync="TRUE">REQUIRED: Northern-most coordinate of the limit of coverage expressed in latitude.</northbc><southbc Sync="TRUE">REQUIRED: Southern-most coordinate of the limit of coverage expressed in latitude.</southbc></bounding></spdom><keywords><theme><themekt>REQUIRED: Reference to a formally registered thesaurus or a similar authoritative source of theme keywords.</themekt><themekey>REQUIRED: Common-use word or phrase used to describe the subject of the data set.</themekey></theme></keywords><accconst>REQUIRED: Restrictions and legal prerequisites for accessing the data set.</accconst><useconst>REQUIRED: Restrictions and legal prerequisites for using the data set after access is granted.</useconst><natvform Sync="TRUE">File Geodatabase Feature Class</natvform></idinfo><dataIdInfo><envirDesc Sync="TRUE">Microsoft Windows XP Version 5.1 (Build 2600) Service Pack 3; ESRI ArcGIS 10.0.2.3200</envirDesc><dataLang><languageCode Sync="TRUE" value="en" country="CA"></languageCode></dataLang><idCitation><resTitle Sync="TRUE">prot_areas_p</resTitle><presForm><PresFormCd value="005"></PresFormCd></presForm></idCitation><descKeys><thesaName uuidref="723f6998-058e-11dc-8314-0800200c9a66"></thesaName><keyword Sync="TRUE">002</keyword></descKeys><spatRpType><SpatRepTypCd value="001"></SpatRepTypCd></spatRpType></dataIdInfo><metainfo><langmeta Sync="TRUE">en</langmeta><metstdn Sync="TRUE">FGDC Content Standards for Digital Geospatial Metadata</metstdn><metstdv Sync="TRUE">FGDC-STD-001-1998</metstdv><mettc Sync="TRUE">local time</mettc><metc><cntinfo><cntorgp><cntper>REQUIRED: The person responsible for the metadata information.</cntper><cntorg>REQUIRED: The organization responsible for the metadata information.</cntorg></cntorgp><cntaddr><addrtype>REQUIRED: The mailing and/or physical address for the organization or individual.</addrtype><city>REQUIRED: The city of the address.</city><state>REQUIRED: The state or province of the address.</state><postal>REQUIRED: The ZIP or other postal code of the address.</postal></cntaddr><cntvoice>REQUIRED: The telephone number by which individuals can speak to the organization or individual.</cntvoice></cntinfo></metc><metd Sync="TRUE">20101201</metd></metainfo><mdLang><languageCode Sync="TRUE" value="en"></languageCode></mdLang><mdStanName Sync="TRUE">ISO 19115 Geographic Information - Metadata</mdStanName><mdStanVer Sync="TRUE">DIS_ESRI1.0</mdStanVer><mdChar><CharSetCd Sync="TRUE" value="004"></CharSetCd></mdChar><mdHrLv><ScopeCd Sync="TRUE" value="005"></ScopeCd></mdHrLv><mdHrLvName Sync="TRUE">dataset</mdHrLvName><distinfo><resdesc Sync="TRUE">Downloadable Data</resdesc></distinfo><distInfo><distributor><distorTran><onLineSrc><orDesc Sync="TRUE">002</orDesc><linkage Sync="TRUE">file://\\s0-bsc-fs02\Atlas\Maps\ReferenceMaps\Territories4m\Year2010\terr4M_old_layers.gdb</linkage><protocol Sync="TRUE">Local Area Network</protocol></onLineSrc></distorTran><distorFormat><formatName Sync="TRUE">File Geodatabase Feature Class</formatName></distorFormat></distributor><distFormat><formatName Sync="TRUE">Shapefile</formatName></distFormat><distTranOps><transSize Sync="TRUE">0.000</transSize></distTranOps></distInfo><spdoinfo><direct Sync="TRUE">Vector</direct><ptvctinf><esriterm Name="prot_areas_p"><efeatyp Sync="TRUE">Simple</efeatyp><efeageom Sync="TRUE">4</efeageom><esritopo Sync="TRUE">FALSE</esritopo><efeacnt Sync="TRUE">0</efeacnt><spindex Sync="TRUE">FALSE</spindex><linrefer Sync="TRUE">FALSE</linrefer></esriterm></ptvctinf></spdoinfo><spref><horizsys><cordsysn><geogcsn Sync="TRUE">GCS_Clarke_1866</geogcsn><projcsn Sync="TRUE">Clarke_1866_Lambert_Conformal_Conic</projcsn></cordsysn><planar><planci><plance Sync="TRUE">coordinate pair</plance><plandu Sync="TRUE">meters</plandu><coordrep><absres Sync="TRUE">0.000500</absres><ordres Sync="TRUE">0.000500</ordres></coordrep></planci></planar><geodetic><horizdn Sync="TRUE">D_Clarke_1866</horizdn><ellips Sync="TRUE">Clarke 1866</ellips><semiaxis Sync="TRUE">6378206.400000</semiaxis><denflat Sync="TRUE">294.978698</denflat></geodetic></horizsys><vertdef><altsys><altenc Sync="TRUE">Explicit elevation coordinate included with horizontal coordinates</altenc><altres Sync="TRUE">0.000100</altres></altsys></vertdef></spref><refSysInfo><RefSystem><refSysID><identCode Sync="TRUE" code="0">Clarke_1866_Lambert_Conformal_Conic</identCode></refSysID></RefSystem></refSysInfo><spatRepInfo><VectSpatRep><topLvl><TopoLevCd Sync="TRUE" value="001"></TopoLevCd></topLvl><geometObjs Name="park_polygon"><geoObjTyp><GeoObjTypCd Sync="TRUE" value="002"></GeoObjTypCd><geoObjCnt Sync="TRUE">0</geoObjCnt></geoObjTyp><geoObjCnt Sync="TRUE">0</geoObjCnt></geometObjs></VectSpatRep></spatRepInfo><eainfo><detailed Name="prot_areas_p"><enttyp><enttypl Sync="TRUE">prot_areas_p</enttypl><enttypt Sync="TRUE">Feature Class</enttypt><enttypc Sync="TRUE">0</enttypc></enttyp><attr><attrlabl Sync="TRUE">FID</attrlabl><attalias Sync="TRUE">FID</attalias><attrtype Sync="TRUE">OID</attrtype><attwidth Sync="TRUE">4</attwidth><atprecis Sync="TRUE">0</atprecis><attscale Sync="TRUE">0</attscale><attrdef Sync="TRUE">Internal feature number.</attrdef><attrdefs Sync="TRUE">ESRI</attrdefs><attrdomv><udom Sync="TRUE">Sequential unique whole numbers that are automatically generated.</udom></attrdomv></attr><attr><attrlabl Sync="TRUE">Shape</attrlabl><attalias Sync="TRUE">Shape</attalias><attrtype Sync="TRUE">Geometry</attrtype><attwidth Sync="TRUE">0</attwidth><atprecis Sync="TRUE">0</atprecis><attscale Sync="TRUE">0</attscale><attrdef Sync="TRUE">Feature geometry.</attrdef><attrdefs Sync="TRUE">ESRI</attrdefs><attrdomv><udom Sync="TRUE">Coordinates defining the features.</udom></attrdomv></attr><attr><attrlabl Sync="TRUE">CARTO_UID</attrlabl><attalias Sync="TRUE">CARTO_UID</attalias><attrtype Sync="TRUE">Integer</attrtype><attwidth Sync="TRUE">9</attwidth><atprecis Sync="TRUE">9</atprecis><attscale Sync="TRUE">0</attscale></attr><attr><attrlabl Sync="TRUE">Shape_Leng</attrlabl><attalias Sync="TRUE">Shape_Leng</attalias><attrtype Sync="TRUE">Double</attrtype><attwidth Sync="TRUE">19</attwidth><atprecis Sync="TRUE">0</atprecis><attscale Sync="TRUE">0</attscale></attr><attr><attrlabl Sync="TRUE">CLASS</attrlabl><attalias Sync="TRUE">CLASS</attalias><attrtype Sync="TRUE">SmallInteger</attrtype><attwidth Sync="TRUE">4</attwidth><atprecis Sync="TRUE">4</atprecis><attscale Sync="TRUE">0</attscale></attr><attr><attrlabl Sync="TRUE">NAME_EN</attrlabl><attalias Sync="TRUE">NAME_EN</attalias><attrtype Sync="TRUE">String</attrtype><attwidth Sync="TRUE">250</attwidth><atprecis Sync="TRUE">0</atprecis><attscale Sync="TRUE">0</attscale></attr><attr><attrlabl Sync="TRUE">NOM_FR</attrlabl><attalias Sync="TRUE">NOM_FR</attalias><attrtype Sync="TRUE">String</attrtype><attwidth Sync="TRUE">250</attwidth><atprecis Sync="TRUE">0</atprecis><attscale Sync="TRUE">0</attscale></attr><attr><attrlabl Sync="TRUE">FEATURE_E</attrlabl><attalias Sync="TRUE">FEATURE_E</attalias><attrtype Sync="TRUE">String</attrtype><attwidth Sync="TRUE">50</attwidth><atprecis Sync="TRUE">0</atprecis><attscale Sync="TRUE">0</attscale></attr><attr><attrlabl Sync="TRUE">FEATURE_F</attrlabl><attalias Sync="TRUE">FEATURE_F</attalias><attrtype Sync="TRUE">String</attrtype><attwidth Sync="TRUE">50</attwidth><atprecis Sync="TRUE">0</atprecis><attscale Sync="TRUE">0</attscale></attr><attr><attrlabl Sync="TRUE">Shape_Area</attrlabl><attalias Sync="TRUE">Shape_Area</attalias><attrtype Sync="TRUE">Double</attrtype><attwidth Sync="TRUE">19</attwidth><atprecis Sync="TRUE">0</atprecis><attscale Sync="TRUE">0</attscale><attrdef Sync="TRUE">Area of feature in internal units squared.</attrdef><attrdefs Sync="TRUE">ESRI</attrdefs><attrdomv><udom Sync="TRUE">Positive real numbers that are automatically generated.</udom></attrdomv></attr><attr><attrlabl Sync="TRUE">WATER_COMP</attrlabl><attalias Sync="TRUE">WATER_COMP</attalias><attrtype Sync="TRUE">SmallInteger</attrtype><attwidth Sync="TRUE">4</attwidth><atprecis Sync="TRUE">4</atprecis><attscale Sync="TRUE">0</attscale></attr></detailed></eainfo><mdDateSt Sync="TRUE">20120416</mdDateSt></metadata>
